<gexf xmlns="http://www.gexf.net/1.2draft" xmlns:xsi="http://www.w3.org/2001/XMLSchema-instance" xsi:schemaLocation="http://www.gexf.net/1.2draft http://www.gexf.net/1.2draft/gexf.xsd" version="1.2">
  <meta lastmodifieddate="2023-05-04">
    <creator>NetworkX 3.1</creator>
  </meta>
  <graph defaultedgetype="directed" mode="static" name="">
    <attributes mode="static" class="node">
      <attribute id="0" title="p_fail" type="double" />
      <attribute id="1" title="retries" type="long" />
    </attributes>
    <nodes>
      <node id="0" label="0" />
      <node id="1" label="1">
        <attvalues>
          <attvalue for="0" value="0.025357018055294247" />
          <attvalue for="1" value="1" />
        </attvalues>
      </node>
      <node id="2" label="2">
        <attvalues>
          <attvalue for="0" value="0.11688756781647175" />
          <attvalue for="1" value="2" />
        </attvalues>
      </node>
      <node id="3" label="3">
        <attvalues>
          <attvalue for="0" value="0.09477798164325625" />
          <attvalue for="1" value="2" />
        </attvalues>
      </node>
      <node id="4" label="4">
        <attvalues>
          <attvalue for="0" value="0.24078047811440784" />
          <attvalue for="1" value="1" />
        </attvalues>
      </node>
      <node id="5" label="5">
        <attvalues>
          <attvalue for="0" value="0.25631344394514854" />
          <attvalue for="1" value="1" />
        </attvalues>
      </node>
      <node id="6" label="6">
        <attvalues>
          <attvalue for="0" value="0.17143073748728138" />
          <attvalue for="1" value="1" />
        </attvalues>
      </node>
      <node id="7" label="7">
        <attvalues>
          <attvalue for="0" value="0.08676343449345832" />
          <attvalue for="1" value="2" />
        </attvalues>
      </node>
      <node id="8" label="8">
        <attvalues>
          <attvalue for="0" value="0.16559039844492787" />
          <attvalue for="1" value="1" />
        </attvalues>
      </node>
      <node id="9" label="9">
        <attvalues>
          <attvalue for="0" value="0.024892311030503017" />
          <attvalue for="1" value="1" />
        </attvalues>
      </node>
      <node id="10" label="10">
        <attvalues>
          <attvalue for="0" value="0.07536168822716574" />
          <attvalue for="1" value="1" />
        </attvalues>
      </node>
      <node id="11" label="11">
        <attvalues>
          <attvalue for="0" value="0.148276604919362" />
          <attvalue for="1" value="1" />
        </attvalues>
      </node>
      <node id="12" label="12">
        <attvalues>
          <attvalue for="0" value="0.1509446276051296" />
          <attvalue for="1" value="2" />
        </attvalues>
      </node>
      <node id="13" label="13">
        <attvalues>
          <attvalue for="0" value="0.24163361166260006" />
          <attvalue for="1" value="1" />
        </attvalues>
      </node>
      <node id="14" label="14">
        <attvalues>
          <attvalue for="0" value="0.2782523243477816" />
          <attvalue for="1" value="1" />
        </attvalues>
      </node>
      <node id="15" label="15">
        <attvalues>
          <attvalue for="0" value="0.10771660452237046" />
          <attvalue for="1" value="2" />
        </attvalues>
      </node>
      <node id="16" label="16">
        <attvalues>
          <attvalue for="0" value="0.026664534265550308" />
          <attvalue for="1" value="1" />
        </attvalues>
      </node>
      <node id="17" label="17">
        <attvalues>
          <attvalue for="0" value="0.07733782621186062" />
          <attvalue for="1" value="1" />
        </attvalues>
      </node>
      <node id="18" label="18">
        <attvalues>
          <attvalue for="0" value="0.034481580661089875" />
          <attvalue for="1" value="2" />
        </attvalues>
      </node>
      <node id="19" label="19">
        <attvalues>
          <attvalue for="0" value="0.033359874207871475" />
          <attvalue for="1" value="2" />
        </attvalues>
      </node>
      <node id="20" label="20">
        <attvalues>
          <attvalue for="0" value="0.06645960985427882" />
          <attvalue for="1" value="2" />
        </attvalues>
      </node>
      <node id="21" label="21">
        <attvalues>
          <attvalue for="0" value="0.2283667623404778" />
          <attvalue for="1" value="2" />
        </attvalues>
      </node>
      <node id="22" label="22">
        <attvalues>
          <attvalue for="0" value="0.08858191743364824" />
          <attvalue for="1" value="2" />
        </attvalues>
      </node>
      <node id="23" label="23">
        <attvalues>
          <attvalue for="0" value="0.26650452415876985" />
          <attvalue for="1" value="1" />
        </attvalues>
      </node>
      <node id="24" label="24">
        <attvalues>
          <attvalue for="0" value="0.24865016931039763" />
          <attvalue for="1" value="2" />
        </attvalues>
      </node>
    </nodes>
    <edges>
      <edge source="0" target="14" id="0" />
      <edge source="0" target="7" id="1" />
      <edge source="0" target="19" id="2" />
      <edge source="0" target="24" id="3" />
      <edge source="2" target="20" id="4" />
      <edge source="3" target="10" id="5" />
      <edge source="3" target="22" id="6" />
      <edge source="4" target="16" id="7" />
      <edge source="4" target="23" id="8" />
      <edge source="7" target="15" id="9" />
      <edge source="8" target="3" id="10" />
      <edge source="9" target="13" id="11" />
      <edge source="10" target="9" id="12" />
      <edge source="11" target="5" id="13" />
      <edge source="11" target="12" id="14" />
      <edge source="11" target="8" id="15" />
      <edge source="12" target="17" id="16" />
      <edge source="13" target="2" id="17" />
      <edge source="16" target="1" id="18" />
      <edge source="16" target="18" id="19" />
      <edge source="18" target="6" id="20" />
      <edge source="18" target="21" id="21" />
      <edge source="19" target="11" id="22" />
      <edge source="24" target="4" id="23" />
    </edges>
  </graph>
</gexf>